ipfinder.py
ipfinder-0.2.dist-info/DESCRIPTION.rst
ipfinder-0.2.dist-info/METADATA
ipfinder-0.2.dist-info/RECORD
ipfinder-0.2.dist-info/WHEEL
ipfinder-0.2.dist-info/metadata.json
ipfinder-0.2.dist-info/top_level.txt
