Metadata-Version: 2.0
Name: ipfinder
Version: 0.2
Summary: Simple library to grab an external IP using HTTPS.
Home-page: http://packages.python.org/ipfinder
Author: Joshua Yabut
Author-email: yabut.joshua@gmail.com
License: BSD
Keywords: iplookup ip find whois
Platform: UNKNOWN
Classifier: Development Status :: 4 - Beta
Classifier: Topic :: Utilities
Classifier: License :: OSI Approved :: BSD License
Requires-Dist: requests
